template_log_parser/__init__.py
template_log_parser/built_ins.py
template_log_parser/column_functions.py
template_log_parser/log_functions.py
template_log_parser/log_type_classes.py
template_log_parser/pre_df_functions.py
template_log_parser/templates/__init__.py
template_log_parser/templates/debian_templates.py
template_log_parser/templates/definitions.py
template_log_parser/templates/kodi_templates.py
template_log_parser/templates/omada_templates.py
template_log_parser/templates/omv_templates.py
template_log_parser/templates/pfsense_templates.py
template_log_parser/templates/pihole_templates.py
template_log_parser/templates/synology_templates.py
template_log_parser/templates/template_functions.py
template_log_parser/templates/ubuntu_templates.py
template_log_parser-0.8.1.dist-info/licenses/LICENSE
template_log_parser-0.8.1.dist-info/METADATA
template_log_parser-0.8.1.dist-info/WHEEL
template_log_parser-0.8.1.dist-info/top_level.txt
template_log_parser-0.8.1.dist-info/RECORD
