Metadata-Version: 2.4
Name: template-log-parser
Version: 0.8.1
Summary: Parsing Log Files With User Defined Templates
Author-email: Caleb Yourison <caleb.yourison@gmail.com>
License: MIT License
Project-URL: homepage, https://github.com/calebyourison/simple_template_log_parser
Keywords: log,parse,template
Classifier: Development Status :: 3 - Alpha
Classifier: Programming Language :: Python :: 3
Requires-Python: >=3.9
License-File: LICENSE
Requires-Dist: pandas>=2.0.0
Requires-Dist: parse==1.20.2
Dynamic: license-file
